blizzardAPI/__init__.py
blizzardAPI/api.py
blizzardAPI/blizzard_api.py
blizzardAPI/battlenet/__init__.py
blizzardAPI/battlenet/battlenet_api.py
blizzardAPI/battlenet/battlenet_oauth.py
blizzardAPI/exceptions/__init__.py
blizzardAPI/exceptions/handler.py
blizzardAPI/tests/__init__.py
blizzardAPI/tests/conftest.py
blizzardAPI/world_of_warcraft/__init__.py
blizzardAPI/world_of_warcraft/wow_api.py
blizzardAPI/world_of_warcraft/game_data/__init__.py
blizzardAPI/world_of_warcraft/game_data/achievement.py
blizzardAPI/world_of_warcraft/game_data/auction_house.py
blizzardAPI/world_of_warcraft/game_data/azerite_essence.py
blizzardAPI/world_of_warcraft/game_data/connected_realm.py
blizzardAPI/world_of_warcraft/game_data/covenant.py
blizzardAPI/world_of_warcraft/game_data/creature.py
blizzardAPI/world_of_warcraft/game_data/guild_crest.py
blizzardAPI/world_of_warcraft/game_data/heirloom.py
blizzardAPI/world_of_warcraft/game_data/item.py
blizzardAPI/world_of_warcraft/game_data/journal.py
blizzardAPI/world_of_warcraft/game_data/media.py
blizzardAPI/world_of_warcraft/game_data/modified_crafting.py
blizzardAPI/world_of_warcraft/game_data/mount.py
blizzardAPI/world_of_warcraft/game_data/mythic_keystone_affix.py
blizzardAPI/world_of_warcraft/game_data/mythic_keystone_dungeon.py
blizzardAPI/world_of_warcraft/game_data/mythic_keystone_leaderboard.py
blizzardAPI/world_of_warcraft/game_data/mythic_raid_leaderboard.py
blizzardAPI/world_of_warcraft/game_data/pet.py
blizzardAPI/world_of_warcraft/game_data/playable_class.py
blizzardAPI/world_of_warcraft/game_data/playable_race.py
blizzardAPI/world_of_warcraft/game_data/playable_specialization.py
blizzardAPI/world_of_warcraft/game_data/power_type.py
blizzardAPI/world_of_warcraft/game_data/profession.py
blizzardAPI/world_of_warcraft/game_data/pvp_season.py
blizzardAPI/world_of_warcraft/game_data/pvp_tier.py
blizzardAPI/world_of_warcraft/game_data/quest.py
blizzardAPI/world_of_warcraft/game_data/realm.py
python_ndev_blizzardapi-0.2.3.dist-info/METADATA
python_ndev_blizzardapi-0.2.3.dist-info/WHEEL
python_ndev_blizzardapi-0.2.3.dist-info/top_level.txt
python_ndev_blizzardapi-0.2.3.dist-info/RECORD
