Metadata-Version: 2.1
Name: python-ndev-blizzardapi
Version: 0.2.3
Summary: Python module created to integrate your Python project with the Blizzard API
Home-page: https://github.com/natanrmaia/python-ndev-blizzardapi
Author: natanrmaia
Author-email: contato@natanael.dev.br
Project-URL: Documentation, https://python-ndev-blizzardapi.readthedocs.io/en/latest/
Project-URL: Source, https://github.com/natanrmaia/python-ndev-blizzardapi
Project-URL: Bug Reports, https://github.com/natanrmaia/python-ndev-blizzardapi/issues
Classifier: Programming Language :: Python :: 3
Classifier: License :: OSI Approved :: MIT License
Classifier: Operating System :: OS Independent
Requires-Dist: requests >=2.28.2
Requires-Dist: python-dotenv >=1.0.0
